brainf/__init__.py
brainf/__main__.py
brainf/cli.py
brainf/code.py
brainf/interpreter.py
brainf/memory.py
brainf-0.0.1.data/scripts/brainfuck.py
brainf-0.0.1.dist-info/METADATA
brainf-0.0.1.dist-info/RECORD
brainf-0.0.1.dist-info/WHEEL
brainf-0.0.1.dist-info/top_level.txt
