Metadata-Version: 2.1
Name: brainf
Version: 0.0.1
Summary: Brainfuck interpreter
Home-page: https://github.com/bzaczynski/brainf
Author: Bartosz Zaczyński
Author-email: bartosz.zaczynski@gmail.com
License: MIT
Download-URL: https://github.com/bzaczynski/brainf/archive/master.zip
Keywords: brainfuck interpreter brainf
Platform: UNKNOWN
Classifier: Development Status :: 3 - Alpha
Classifier: License :: OSI Approved :: MIT License
Classifier: Programming Language :: Python :: 3.7
Classifier: Topic :: Software Development :: Interpreters
